LICENSE.txt
MANIFEST.in
README.md
requirements.txt
setup.cfg
setup.py
bitcoin_price_api.egg-info/PKG-INFO
bitcoin_price_api.egg-info/SOURCES.txt
bitcoin_price_api.egg-info/dependency_links.txt
bitcoin_price_api.egg-info/requires.txt
bitcoin_price_api.egg-info/top_level.txt
exchanges/__init__.py
exchanges/base.py
exchanges/bitfinex.py
exchanges/bitmex.py
exchanges/bitstamp.py
exchanges/bitvc.py
exchanges/coinapult.py
exchanges/coindesk.py
exchanges/futures796.py
exchanges/helpers.py
exchanges/huobi.py
exchanges/kraken.py
exchanges/okcoin.py
exchanges/poloniex.py