Metadata-Version: 1.0
Name: bitcoin-price-api
Version: 0.0.3
Summary: API's for bitcoin exchanges
Home-page: https://github.com/dursk/bitcoin-price-api
Author: Matthew Madurski
Author-email: madurskimr@gmail.com
License: MIT
Platform: UNKNOWN
